skeleton_plot/__init__.py
skeleton_plot/plot_tools.py
skeleton_plot/skel_io.py
skeleton_plot/utils.py
skeleton_plot-0.1.0.dist-info/METADATA
skeleton_plot-0.1.0.dist-info/WHEEL
skeleton_plot-0.1.0.dist-info/top_level.txt
skeleton_plot-0.1.0.dist-info/RECORD
