Metadata-Version: 2.4
Name: skeleton_plot
Version: 0.1.0
Summary: package for plotting skeletons
Home-page: https://github.com/AllenInstitute/skeleton_plot
Author: Emily Joyce, Forrest Collman, Casey Schneider-Mizell
Author-email: emily.joyce@alleninstitute.org, forrestc@alleninstitute.org,caseys@alleninstitute.org,
Requires-Dist: numpy
Requires-Dist: matplotlib
Requires-Dist: meshparty
Requires-Dist: pandas
Provides-Extra: cloud
Requires-Dist: caveclient>=4.0.0; extra == "cloud"
Requires-Dist: cloudfiles; extra == "cloud"
Dynamic: author
Dynamic: author-email
Dynamic: home-page
Dynamic: provides-extra
Dynamic: requires-dist
Dynamic: summary
